finsim/__init__.py
finsim/data/__init__.py
finsim/data/finnhub.py
finsim/data/preader.py
finsim/data/quandl.py
finsim/estimate/__init__.py
finsim/estimate/constants.py
finsim/estimate/fit.py
finsim/estimate/risk.py
finsim/estimate/native/__init__.py
finsim/estimate/native/pyfit.py
finsim/estimate/native/pyrisk.py
finsim/portfolio/__init__.py
finsim/portfolio/create.py
finsim/portfolio/dynamic.py
finsim/portfolio/helper.py
finsim/portfolio/portfolio.py
finsim/portfolio/optimize/__init__.py
finsim/portfolio/optimize/metrics.py
finsim/portfolio/optimize/numerics.py
finsim/portfolio/optimize/policy.py
finsim/portfolio/optimize/native/__init__.py
finsim/portfolio/optimize/native/pymetrics.py
finsim/retrieve_stock_symbols_cli/__init__.py
finsim/retrieve_stock_symbols_cli/cli.py
finsim/schemas/__init__.py
finsim/schemas/portfolios.py
finsim/simulation/__init__.py
finsim/simulation/stock.py
finsim/tech/__init__.py
finsim/tech/ma.py
finsim-1.2.1.dist-info/licenses/LICENSE
finsim-1.2.1.dist-info/METADATA
finsim-1.2.1.dist-info/WHEEL
finsim-1.2.1.dist-info/entry_points.txt
finsim-1.2.1.dist-info/top_level.txt
finsim-1.2.1.dist-info/RECORD
