Metadata-Version: 2.4
Name: finsim
Version: 1.2.1
Summary: Financial simulation and inference
Author-email: Kwan Yuet Stephen Ho <stephenhky@yahoo.com.hk>
License: LGPL
Project-URL: Repository, https://github.com/stephenhky/FinanceSimulation
Project-URL: Issues, https://github.com/stephenhky/FinanceSimulation/issues
Project-URL: Documentation, https://financesimulation.readthedocs.io
Keywords: simulation,finance,quantitative finance,inference,portfolio analysis
Classifier: Topic :: Scientific/Engineering :: Mathematics
Classifier: Topic :: Software Development :: Libraries :: Python Modules
Classifier: Topic :: Software Development :: Version Control :: Git
Classifier: Programming Language :: Python :: 3.10
Classifier: Programming Language :: Python :: 3.11
Classifier: Programming Language :: Python :: 3.12
Classifier: Programming Language :: Python :: 3.13
Classifier: Intended Audience :: Science/Research
Classifier: Intended Audience :: Developers
Classifier: Intended Audience :: Financial and Insurance Industry
Requires-Python: >=3.10
License-File: LICENSE
Requires-Dist: numpy>=1.24.0
Requires-Dist: scipy>=1.10.0
Requires-Dist: requests>=2.31.0
Requires-Dist: pandas>=1.5.0
Requires-Dist: quandl>=3.5.0
Requires-Dist: tqdm>=4.49.0
Requires-Dist: tables>=3.8.5
Requires-Dist: yfinance>=0.2.59
Requires-Dist: openpyxl>=3.1.0
Requires-Dist: numba
Requires-Dist: typing-extensions
Requires-Dist: pydantic
Provides-Extra: test
Requires-Dist: unittest2; extra == "test"
Requires-Dist: pytest; extra == "test"
Provides-Extra: docs
Requires-Dist: sphinx>=4.0.0; extra == "docs"
Requires-Dist: sphinx-rtd-theme>=1.0.0; extra == "docs"
Dynamic: license-file
